{
  "blocks": {
    "languageVersion": 0,
    "blocks": [
      {
        "type": "tactigon_shape_function",
        "id": "0!($UF`7TQyU:=g^AFaC",
        "x": 130,
        "y": 130,
        "deletable": false,
        "editable": false,
        "icons": {
          "comment": {
            "text": "This is the main function that runs your code. Any code blocks you add to this section will be executed.",
            "pinned": false,
            "height": 80,
            "width": 160
          }
        },
        "fields": {
          "NAME": "app"
        },
        "inputs": {
          "BODY": {
            "block": {
              "type": "tactigon_shape_debug",
              "id": "[!CboH0GfY;zFTLJ{m54",
              "inputs": {
                "TEXT": {
                  "shadow": {
                    "type": "text",
                    "id": "41+yy{Jz_zMSPkacZbvN",
                    "fields": {
                      "TEXT": "abc"
                    }
                  },
                  "block": {
                    "type": "device_last_telemetry",
                    "id": "L6UkPFTajbfxhZTe)*~;",
                    "inputs": {
                      "device": {
                        "shadow": {
                          "type": "device_list",
                          "id": "WnduaBf/~#{31EJjr2OM",
                          "fields": {
                            "device": "fb906550-4f5a-11ef-850d-a7a8b5a94c63"
                          }
                        }
                      },
                      "keys": {
                        "shadow": {
                          "type": "text",
                          "id": "l[O3.xVYOE!nc=cTGb;O",
                          "fields": {
                            "TEXT": ""
                          }
                        }
                      }
                    }
                  }
                }
              },
              "next": {
                "block": {
                  "type": "tactigon_shape_debug",
                  "id": "/m?+djBU:VH#pw)!+he4",
                  "inputs": {
                    "TEXT": {
                      "shadow": {
                        "type": "text",
                        "id": "41+yy{Jz_zMSPkacZbvN",
                        "fields": {
                          "TEXT": "abc"
                        }
                      },
                      "block": {
                        "type": "device_attr",
                        "id": "-`*C}I66;IX^[Oqidzld",
                        "inputs": {
                          "device": {
                            "shadow": {
                              "type": "device_list",
                              "id": "=JRUw=na:LH3CSj-k+V@",
                              "fields": {
                                "device": "fb906550-4f5a-11ef-850d-a7a8b5a94c63"
                              }
                            }
                          },
                          "scope": {
                            "shadow": {
                              "type": "scope_list",
                              "id": "`~H2_TVaVB]yPw{R48[R",
                              "fields": {
                                "scope": "SERVER_SCOPE"
                              }
                            }
                          },
                          "keys": {
                            "shadow": {
                              "type": "text",
                              "id": "`NHdgRL{au}3n4!vV5wz",
                              "fields": {
                                "TEXT": "alarm_threshold"
                              }
                            }
                          }
                        }
                      }
                    }
                  },
                  "next": {
                    "block": {
                      "type": "tactigon_shape_debug",
                      "id": "A6b:V*CFG,K7-oT8~$CV",
                      "inputs": {
                        "TEXT": {
                          "shadow": {
                            "type": "text",
                            "id": "ba;=%k};a)bhXk!lw{ya",
                            "fields": {
                              "TEXT": "abc"
                            }
                          },
                          "block": {
                            "type": "device_alarm",
                            "id": "$iwG%CqVr,Jg*i(**Wfd",
                            "inputs": {
                              "device": {
                                "shadow": {
                                  "type": "device_list",
                                  "id": "qX38LIkkl]pIA4_aty]y",
                                  "fields": {
                                    "device": "fb906550-4f5a-11ef-850d-a7a8b5a94c63"
                                  }
                                }
                              },
                              "severity": {
                                "shadow": {
                                  "type": "alarm_severity_list",
                                  "id": "88MUTm,qx#s-UTi{MJ{t",
                                  "fields": {
                                    "severity": "CRITICAL"
                                  }
                                }
                              },
                              "search_status": {
                                "shadow": {
                                  "type": "alarm_search_status_list",
                                  "id": "Z)hnabcX2-#GrH]M.$8(",
                                  "fields": {
                                    "search_status": "ACTIVE"
                                  }
                                }
                              }
                            }
                          }
                        }
                      },
                      "next": {
                        "block": {
                          "type": "tactigon_shape_debug",
                          "id": "%Fkq|mAk]2t-PSU[s{vE",
                          "inputs": {
                            "TEXT": {
                              "shadow": {
                                "type": "text",
                                "id": "ba;=%k};a)bhXk!lw{ya",
                                "fields": {
                                  "TEXT": "abc"
                                }
                              },
                              "block": {
                                "type": "send_device_last_telemetry",
                                "id": "Zmw@$CZy1Hsk(+o!mixz",
                                "inputs": {
                                  "device": {
                                    "shadow": {
                                      "type": "device_list",
                                      "id": "`mMRm0KVv^*QZ=ih?PAq",
                                      "fields": {
                                        "device": "fb906550-4f5a-11ef-850d-a7a8b5a94c63"
                                      }
                                    }
                                  },
                                  "key": {
                                    "shadow": {
                                      "type": "text",
                                      "id": "Q2W6UMa{kZJ,$oH;b|ns",
                                      "fields": {
                                        "TEXT": "temperature_zion"
                                      }
                                    }
                                  },
                                  "payload": {
                                    "shadow": {
                                      "type": "text",
                                      "id": ".x0,@Fo@qQ^T8EnT5@_N",
                                      "fields": {
                                        "TEXT": ""
                                      }
                                    },
                                    "block": {
                                      "type": "math_number",
                                      "id": "|XW,zUM3]zSOfUIOyeA*",
                                      "fields": {
                                        "NUM": 23.5
                                      }
                                    }
                                  }
                                }
                              }
                            }
                          },
                          "next": {
                            "block": {
                              "type": "tactigon_shape_debug",
                              "id": "}al!c[ENH:#?R*8%upu!",
                              "inputs": {
                                "TEXT": {
                                  "shadow": {
                                    "type": "text",
                                    "id": "ba;=%k};a)bhXk!lw{ya",
                                    "fields": {
                                      "TEXT": "abc"
                                    }
                                  },
                                  "block": {
                                    "type": "send_device_attr",
                                    "id": "fYdu0uFePSJz5XY+FGy{",
                                    "inputs": {
                                      "device": {
                                        "shadow": {
                                          "type": "device_list",
                                          "id": "TJQ^Havi9$k~V`[e7Al6",
                                          "fields": {
                                            "device": "fb906550-4f5a-11ef-850d-a7a8b5a94c63"
                                          }
                                        }
                                      },
                                      "scope": {
                                        "shadow": {
                                          "type": "scope_list",
                                          "id": "!@wIBX2kYm6tw@)VKs~+",
                                          "fields": {
                                            "scope": "SERVER_SCOPE"
                                          }
                                        }
                                      },
                                      "key": {
                                        "shadow": {
                                          "type": "text",
                                          "id": "xz*d0x*A%~Vz[j+SfxuR",
                                          "fields": {
                                            "TEXT": "automatic"
                                          }
                                        }
                                      },
                                      "payload": {
                                        "shadow": {
                                          "type": "text",
                                          "id": "~ybBZ:X/b${EeJh6D=2R",
                                          "fields": {
                                            "TEXT": ""
                                          }
                                        },
                                        "block": {
                                          "type": "logic_boolean",
                                          "id": "Eiu$^f~uH(rO3Y}LmZ+L",
                                          "fields": {
                                            "BOOL": "TRUE"
                                          }
                                        }
                                      }
                                    }
                                  }
                                }
                              }
                            }
                          }
                        }
                      }
                    }
                  }
                }
              }
            }
          }
        }
      }
    ]
  }
}